{
  "header": {
    "height": 60
  },
  "tags": {
    "visible": true,
    "height": 50
  },
  "naiveThemeOverrides": {
    "common": {
      "primaryColor": "#3F8C2E",
      "primaryColorHover": "#4A9D37",
      "primaryColorPressed": "#347827",
      "primaryColorSuppl": "#3F8C2E",
      "infoColor": "#2D6A9F",
      "infoColorHover": "#3A7CB5",
      "infoColorPressed": "#23557F",
      "infoColorSuppl": "#3A7CB5",
      "successColor": "#2F9E44",
      "successColorHover": "#3DAA53",
      "successColorPressed": "#278739",
      "successColorSuppl": "#3DAA53",
      "warningColor": "#D98E18",
      "warningColorHover": "#E8A53E",
      "warningColorPressed": "#B6740D",
      "warningColorSuppl": "#E8A53E",
      "errorColor": "#D94841",
      "errorColorHover": "#E2625B",
      "errorColorPressed": "#B73A34",
      "errorColorSuppl": "#E2625B"
    }
  }
}
